{"2024-05-20-2024-05-20": {"ARG - Medios Misiones - FB": [{"valor": 8, "palabra": "docentes-provincia"}, {"valor": 8, "palabra": "provincia-misiones"}, {"valor": 7, "palabra": "afuera-kretinistas"}, {"valor": 6, "palabra": "kretinistas-afuera"}, {"valor": 5, "palabra": "policial-salario"}, {"valor": 5, "palabra": "salario-docentes"}, {"valor": 5, "palabra": "docentes-personal"}, {"valor": 4, "palabra": "caballero-secretario"}, {"valor": 4, "palabra": "secretario-gremial"}, {"valor": 4, "palabra": "gremial-docentes"}, {"valor": 4, "palabra": "misiones-s___________________________________d"}, {"valor": 4, "palabra": "s___________________________________d-presente"}, {"valor": 4, "palabra": "presente-sentirme"}, {"valor": 4, "palabra": "sentirme-representado"}, {"valor": 4, "palabra": "representado-dirección"}, {"valor": 4, "palabra": "dirección-gremial"}, {"valor": 4, "palabra": "gremial-solicito"}, {"valor": 4, "palabra": "solicito-pronta"}, {"valor": 4, "palabra": "pronta-desafiliación"}, {"valor": 4, "palabra": "desafiliación-docentes"}, {"valor": 4, "palabra": "misiones-haciendo"}, {"valor": 4, "palabra": "haciendo-derechos"}, {"valor": 4, "palabra": "derechos-confiere"}, {"valor": 4, "palabra": "confiere-párrafo"}, {"valor": 4, "palabra": "párrafo-inciso"}, {"valor": 4, "palabra": "inciso-artículo"}, {"valor": 4, "palabra": "artículo-decreto"}, {"valor": 4, "palabra": "decreto-reglamento"}, {"valor": 4, "palabra": "reglamento-asociaciones"}, {"valor": 4, "palabra": "asociaciones-sindicales"}], "ARG - HUGO PASSALACQUA - FB": [{"valor": 2, "palabra": "uniforme-docente"}, {"valor": 2, "palabra": "canasta-básica"}, {"valor": 2, "palabra": "renuncia-passalacqua"}, {"valor": 1, "palabra": "hicieron-policías"}, {"valor": 1, "palabra": "policías-cuando"}, {"valor": 1, "palabra": "cuando-claramente"}, {"valor": 1, "palabra": "claramente-totalmente"}, {"valor": 1, "palabra": "totalmente-distinto"}, {"valor": 1, "palabra": "distinto-passalacqua"}, {"valor": 1, "palabra": "passalacqua-romero"}, {"valor": 1, "palabra": "romero-spinelli"}, {"valor": 1, "palabra": "spinelli-1500000000"}, {"valor": 1, "palabra": "1500000000-fueron"}, {"valor": 1, "palabra": "fueron-empresas"}, {"valor": 1, "palabra": "empresas-testaferros"}, {"valor": 1, "palabra": "testaferros-paalacua"}, {"valor": 1, "palabra": "paalacua-póngase"}, {"valor": 1, "palabra": "póngase-uniforme"}, {"valor": 1, "palabra": "uniforme-policía"}, {"valor": 1, "palabra": "policía-uniforme"}, {"valor": 1, "palabra": "docente-uniforme"}, {"valor": 1, "palabra": "uniforme-enfermeros"}, {"valor": 1, "palabra": "enfermeros-doctores"}, {"valor": 1, "palabra": "doctores-sueldito"}, {"valor": 1, "palabra": "sueldito-chiperos"}, {"valor": 1, "palabra": "chiperos-mismos"}, {"valor": 1, "palabra": "mismos-desmerecer"}, {"valor": 1, "palabra": "desmerecer-chiperos"}, {"valor": 1, "palabra": "chiperos-trabajo"}, {"valor": 1, "palabra": "trabajo-palabras"}], "ARG - LUCAS ROMERO SPINELLI - FB": [{"valor": 1, "palabra": "suegro-rovira"}, {"valor": 1, "palabra": "rovira-podrían"}, {"valor": 1, "palabra": "podrían-explicar"}, {"valor": 1, "palabra": "explicar-passalacqua"}, {"valor": 1, "palabra": "passalacqua-suegro"}, {"valor": 1, "palabra": "suegro-carlos"}, {"valor": 1, "palabra": "carlos-eduardo"}, {"valor": 1, "palabra": "eduardo-rovira"}, {"valor": 1, "palabra": "rovira-fueron"}, {"valor": 1, "palabra": "fueron-1500000000"}, {"valor": 1, "palabra": "1500000000-vergüenza"}, {"valor": 1, "palabra": "vergüenza-gobernantes"}, {"valor": 1, "palabra": "gobernantes-licencia"}, {"valor": 1, "palabra": "licencia-laboral"}, {"valor": 1, "palabra": "laboral-estrés"}]}, "2024-05-21-2024-05-21": {"ARG - Medios Misiones - FB": [{"valor": 2, "palabra": "sindicatos-tienen"}, {"valor": 2, "palabra": "tienen-política"}, {"valor": 2, "palabra": "política-oposición"}, {"valor": 2, "palabra": "oposición-argentina"}, {"valor": 2, "palabra": "argentina-mientras"}, {"valor": 2, "palabra": "mientras-revolucionarios"}, {"valor": 2, "palabra": "revolucionarios-estuvieron"}, {"valor": 2, "palabra": "estuvieron-cayados"}, {"valor": 2, "palabra": "cayados-recibiendo"}, {"valor": 2, "palabra": "recibiendo-sobres"}, {"valor": 2, "palabra": "sobres-alberto"}, {"valor": 2, "palabra": "alberto-fernández"}, {"valor": 2, "palabra": "fernández-obviamente"}, {"valor": 2, "palabra": "obviamente-sueldo"}, {"valor": 2, "palabra": "sueldo-miseria"}, {"valor": 2, "palabra": "miseria-cobrar"}, {"valor": 2, "palabra": "cobrar-cobran"}, {"valor": 2, "palabra": "cobran-educación"}, {"valor": 2, "palabra": "educación-seguridad"}, {"valor": 2, "palabra": "seguridad-cuenta"}, {"valor": 2, "palabra": "cuenta-después"}, {"valor": 2, "palabra": "después-sueldo"}, {"valor": 2, "palabra": "sueldo-normalice"}, {"valor": 2, "palabra": "normalice-volverán"}, {"valor": 2, "palabra": "volverán-buscar"}, {"valor": 2, "palabra": "buscar-cualquier"}, {"valor": 2, "palabra": "cualquier-escusa"}, {"valor": 2, "palabra": "escusa-volver"}, {"valor": 2, "palabra": "volver-convulsionar"}, {"valor": 2, "palabra": "convulsionar-argentina"}], "ARG - HUGO PASSALACQUA - FB": [{"valor": 1, "palabra": "impresentable-pueblo"}, {"valor": 1, "palabra": "pueblo-renuncia"}, {"valor": 1, "palabra": "renuncia-gobierno"}, {"valor": 1, "palabra": "gobierno-impresentable"}, {"valor": 1, "palabra": "impresentable-tendremos"}, {"valor": 1, "palabra": "tendremos-memoria"}, {"valor": 1, "palabra": "memoria-preocupen"}, {"valor": 1, "palabra": "preocupen-crotoooii"}, {"valor": 1, "palabra": "crotoooii-crotooooo"}, {"valor": 1, "palabra": "crotooooo-hablen"}, {"valor": 1, "palabra": "hablen-verdad"}, {"valor": 1, "palabra": "verdad-conductores"}, {"valor": 1, "palabra": "conductores-rovira"}, {"valor": 1, "palabra": "rovira-pasalacqua"}, {"valor": 1, "palabra": "pasalacqua-spinelli"}, {"valor": 1, "palabra": "spinelli-crotooooo"}], "ARG - LUCAS ROMERO SPINELLI - FB": []}, "2024-05-22-2024-05-22": {"ARG - Medios Misiones - FB": [{"valor": 2, "palabra": "gobernador-reprima"}, {"valor": 2, "palabra": "reprima-golpistas"}, {"valor": 2, "palabra": "golpistas-malditos"}, {"valor": 2, "palabra": "malditos-entienden"}, {"valor": 2, "palabra": "entienden-buenas"}, {"valor": 2, "palabra": "buenas-quieren"}, {"valor": 2, "palabra": "quieren-acondicionado"}, {"valor": 2, "palabra": "acondicionado-viajar"}, {"valor": 2, "palabra": "viajar-europa"}, {"valor": 2, "palabra": "europa-entienden"}, {"valor": 2, "palabra": "entienden-argentina"}, {"valor": 2, "palabra": "argentina-ajusta"}, {"valor": 1, "palabra": "limpiezal-mejorar"}, {"valor": 1, "palabra": "mejorar-monton"}, {"valor": 1, "palabra": "monton-música"}, {"valor": 1, "palabra": "música-brazilera"}, {"valor": 1, "palabra": "brazilera-opinión"}, {"valor": 1, "palabra": "opinión-futuro"}, {"valor": 1, "palabra": "futuro-temperley"}, {"valor": 1, "palabra": "temperley-felicitaciones"}, {"valor": 1, "palabra": "felicitaciones-éxitos"}, {"valor": 1, "palabra": "éxitos-gobernador"}, {"valor": 1, "palabra": "ajusta-excelente"}, {"valor": 1, "palabra": "excelente-entrenador"}, {"valor": 1, "palabra": "entrenador-lástima"}, {"valor": 1, "palabra": "lástima-supieron"}, {"valor": 1, "palabra": "supieron-comprender"}, {"valor": 1, "palabra": "comprender-presencia"}, {"valor": 1, "palabra": "presencia-fuerza"}, {"valor": 1, "palabra": "fuerza-caraduras"}], "ARG - HUGO PASSALACQUA - FB": [{"valor": 2, "palabra": "aumentos-correspondientes"}, {"valor": 2, "palabra": "jubilados-pensionados"}, {"valor": 2, "palabra": "pensionados-retirados"}, {"valor": 2, "palabra": "retirados-provinciales"}, {"valor": 2, "palabra": "provinciales-empleados"}, {"valor": 2, "palabra": "activos-estado"}, {"valor": 2, "palabra": "estado-provincial"}, {"valor": 2, "palabra": "empleados-públicos"}, {"valor": 2, "palabra": "sustentable-misionera"}, {"valor": 2, "palabra": "parque-industrial"}, {"valor": 1, "palabra": "informo-jueves"}, {"valor": 1, "palabra": "jueves-estarán"}, {"valor": 1, "palabra": "estarán-acreditados"}, {"valor": 1, "palabra": "acreditados-aumentos"}, {"valor": 1, "palabra": "correspondientes-haberes"}, {"valor": 1, "palabra": "haberes-jubilados"}, {"valor": 1, "palabra": "empleados-activos"}, {"valor": 1, "palabra": "provincial-asimismo"}, {"valor": 1, "palabra": "asimismo-miércoles"}, {"valor": 1, "palabra": "miércoles-estará"}, {"valor": 1, "palabra": "estará-acreditado"}, {"valor": 1, "palabra": "acreditado-también"}, {"valor": 1, "palabra": "también-aumentos"}, {"valor": 1, "palabra": "correspondientes-sueldo"}, {"valor": 1, "palabra": "sueldo-complementario"}, {"valor": 1, "palabra": "complementario-aguinaldo"}, {"valor": 1, "palabra": "aguinaldo-jubilados"}, {"valor": 1, "palabra": "públicos-activos"}, {"valor": 1, "palabra": "provincial-finalmente"}, {"valor": 1, "palabra": "finalmente-miércoles"}], "ARG - LUCAS ROMERO SPINELLI - FB": []}, "2024-05-23-2024-05-23": {"ARG - Medios Misiones - FB": [], "ARG - HUGO PASSALACQUA - FB": [{"valor": 1, "palabra": "recuerden-ustedes"}, {"valor": 1, "palabra": "ustedes-votaron"}, {"valor": 1, "palabra": "votaron-misiones"}, {"valor": 1, "palabra": "misiones-nuevos"}, {"valor": 1, "palabra": "nuevos-espacios"}, {"valor": 1, "palabra": "espacios-verdes"}, {"valor": 1, "palabra": "verdes-mañana"}, {"valor": 1, "palabra": "mañana-concretó"}, {"valor": 1, "palabra": "concretó-compra"}, {"valor": 1, "palabra": "compra-donación"}, {"valor": 1, "palabra": "donación-terrenos"}, {"valor": 1, "palabra": "terrenos-hectáreas"}, {"valor": 1, "palabra": "hectáreas-hectáreas"}, {"valor": 1, "palabra": "hectáreas-fundación"}, {"valor": 1, "palabra": "fundación-silvestre"}, {"valor": 1, "palabra": "silvestre-bosque"}, {"valor": 1, "palabra": "bosque-nativo"}, {"valor": 1, "palabra": "nativo-ministerio"}, {"valor": 1, "palabra": "ministerio-ecología"}, {"valor": 1, "palabra": "ecología-permitirá"}, {"valor": 1, "palabra": "permitirá-ampliación"}, {"valor": 1, "palabra": "ampliación-parque"}, {"valor": 1, "palabra": "parque-provincial"}, {"valor": 1, "palabra": "provincial-guardaparque"}, {"valor": 1, "palabra": "guardaparque-horacio"}, {"valor": 1, "palabra": "horacio-forester"}, {"valor": 1, "palabra": "forester-significa"}, {"valor": 1, "palabra": "significa-aporte"}, {"valor": 1, "palabra": "aporte-continuar"}, {"valor": 1, "palabra": "continuar-fortaleciendo"}], "ARG - LUCAS ROMERO SPINELLI - FB": []}, "2024-05-24-2024-05-24": {"ARG - Medios Misiones - FB": [], "ARG - HUGO PASSALACQUA - FB": [{"valor": 3, "palabra": "fuerza-gobernador"}, {"valor": 3, "palabra": "gobernador-afloje"}, {"valor": 3, "palabra": "docentes-policías"}, {"valor": 2, "palabra": "afloje-docentes"}, {"valor": 2, "palabra": "policías-alcanza"}, {"valor": 2, "palabra": "alcanza-tremendos"}, {"valor": 2, "palabra": "tremendos-durante"}, {"valor": 2, "palabra": "pueblo-desperto"}, {"valor": 1, "palabra": "irresponsabletendría-frente"}, {"valor": 1, "palabra": "frente-crisis"}, {"valor": 1, "palabra": "crisis-provincia"}, {"valor": 1, "palabra": "provincia-fuerza"}, {"valor": 1, "palabra": "afloje-golpistas"}, {"valor": 1, "palabra": "golpistas-delincuentes"}, {"valor": 1, "palabra": "delincuentes-uniforme"}, {"valor": 1, "palabra": "uniforme-guardapolvo"}, {"valor": 1, "palabra": "guardapolvo-docentes"}, {"valor": 1, "palabra": "policías-delincuentes"}, {"valor": 1, "palabra": "delincuentes-cortan"}, {"valor": 1, "palabra": "cortan-encapuchados"}, {"valor": 1, "palabra": "encapuchados-quemando"}, {"valor": 1, "palabra": "quemando-atacan"}, {"valor": 1, "palabra": "atacan-edificios"}, {"valor": 1, "palabra": "edificios-públicos"}, {"valor": 1, "palabra": "públicos-circular"}, {"valor": 1, "palabra": "circular-atacan"}, {"valor": 1, "palabra": "atacan-democracia"}, {"valor": 1, "palabra": "democracia-policías"}, {"valor": 1, "palabra": "policías-docentes"}, {"valor": 1, "palabra": "docentes-cortan"}], "ARG - LUCAS ROMERO SPINELLI - FB": [{"valor": 2, "palabra": "docentes-policías"}, {"valor": 1, "palabra": "estuvimos-presentes"}, {"valor": 1, "palabra": "presentes-evento"}, {"valor": 1, "palabra": "evento-industria"}, {"valor": 1, "palabra": "industria-tealera"}, {"valor": 1, "palabra": "tealera-argentina"}, {"valor": 1, "palabra": "argentina-predio"}, {"valor": 1, "palabra": "predio-ferial"}, {"valor": 1, "palabra": "ferial-parque"}, {"valor": 1, "palabra": "parque-conocimiento"}, {"valor": 1, "palabra": "conocimiento-posadas"}, {"valor": 1, "palabra": "posadas-potenciar"}, {"valor": 1, "palabra": "potenciar-cadena"}, {"valor": 1, "palabra": "cadena-productiva"}, {"valor": 1, "palabra": "productiva-rondas"}, {"valor": 1, "palabra": "rondas-negocios"}, {"valor": 1, "palabra": "negocios-oportunidades"}, {"valor": 1, "palabra": "oportunidades-comercialización"}, {"valor": 1, "palabra": "comercialización-escala"}, {"valor": 1, "palabra": "escala-expositores"}, {"valor": 1, "palabra": "expositores-productores"}, {"valor": 1, "palabra": "productores-elaboradores"}, {"valor": 1, "palabra": "elaboradores-sommeliers"}, {"valor": 1, "palabra": "sommeliers-técnicos"}, {"valor": 1, "palabra": "técnicos-profesionales"}, {"valor": 1, "palabra": "profesionales-empresas"}, {"valor": 1, "palabra": "empresas-emprendedores"}, {"valor": 1, "palabra": "emprendedores-misiones"}, {"valor": 1, "palabra": "misiones-tenemos"}, {"valor": 1, "palabra": "tenemos-hectáreas"}]}, "2024-05-25-2024-05-25": {"ARG - Medios Misiones - FB": [], "ARG - HUGO PASSALACQUA - FB": [{"valor": 2, "palabra": "empleados-públicos"}, {"valor": 2, "palabra": "seguir-trabajando"}, {"valor": 2, "palabra": "encuentren-solución"}, {"valor": 2, "palabra": "solución-conflicto"}, {"valor": 2, "palabra": "conflicto-docente"}, {"valor": 2, "palabra": "paguen-sueldos"}, {"valor": 2, "palabra": "fortaleza-sabiduría"}, {"valor": 2, "palabra": "ustedes-perfectamente"}, {"valor": 2, "palabra": "trabajando-tomando"}, {"valor": 1, "palabra": "trabajando-momento"}, {"valor": 1, "palabra": "momento-presidente"}, {"valor": 1, "palabra": "presidente-legislatura"}, {"valor": 1, "palabra": "legislatura-herrera"}, {"valor": 1, "palabra": "herrera-partir"}, {"valor": 1, "palabra": "partir-mañana"}, {"valor": 1, "palabra": "mañana-estarán"}, {"valor": 1, "palabra": "estarán-liquidados"}, {"valor": 1, "palabra": "liquidados-sueldos"}, {"valor": 1, "palabra": "sueldos-empleados"}, {"valor": 1, "palabra": "públicos-misiones"}, {"valor": 1, "palabra": "misiones-detallamos"}, {"valor": 1, "palabra": "detallamos-quedarán"}, {"valor": 1, "palabra": "quedarán-acuerdo"}, {"valor": 1, "palabra": "acuerdo-aumentos"}, {"valor": 1, "palabra": "aumentos-pactados"}, {"valor": 1, "palabra": "pactados-capturo"}, {"valor": 1, "palabra": "capturo-escribir"}, {"valor": 1, "palabra": "escribir-central"}, {"valor": 1, "palabra": "central-politicos"}, {"valor": 1, "palabra": "politicos-insensibles"}], "ARG - LUCAS ROMERO SPINELLI - FB": [{"valor": 2, "palabra": "docentes-policías"}, {"valor": 2, "palabra": "policías-personal"}, {"valor": 1, "palabra": "compartir-manifestantes"}, {"valor": 1, "palabra": "manifestantes-aparecieron"}, {"valor": 1, "palabra": "aparecieron-buscando"}, {"valor": 1, "palabra": "buscando-medios"}, {"valor": 1, "palabra": "medios-nacionales"}, {"valor": 1, "palabra": "nacionales-ustedes"}, {"valor": 1, "palabra": "ustedes-patria"}, {"valor": 1, "palabra": "patria-alguien"}, {"valor": 1, "palabra": "alguien-desfilarán"}, {"valor": 1, "palabra": "desfilarán-drones"}, {"valor": 1, "palabra": "drones-misioneros"}, {"valor": 1, "palabra": "misioneros-aprendido"}, {"valor": 1, "palabra": "aprendido-valores"}, {"valor": 1, "palabra": "valores-empatíamientras"}, {"valor": 1, "palabra": "empatíamientras-mostrás"}, {"valor": 1, "palabra": "mostrás-sonriendo"}, {"valor": 1, "palabra": "sonriendo-tomando"}, {"valor": 1, "palabra": "tomando-calentito"}, {"valor": 1, "palabra": "calentito-docentes"}, {"valor": 1, "palabra": "personal-pasando"}, {"valor": 1, "palabra": "pasando-carencias"}, {"valor": 1, "palabra": "carencias-familias"}, {"valor": 1, "palabra": "familias-porque"}, {"valor": 1, "palabra": "porque-representan"}, {"valor": 1, "palabra": "representan-conviene"}, {"valor": 1, "palabra": "conviene-vergüenza"}, {"valor": 1, "palabra": "vergüenza-debería"}, {"valor": 1, "palabra": "debería-salarios"}]}, "2024-05-26-2024-05-26": {"ARG - Medios Misiones - FB": [], "ARG - HUGO PASSALACQUA - FB": [{"valor": 2, "palabra": "personal-activo"}, {"valor": 2, "palabra": "activo-administración"}, {"valor": 2, "palabra": "administración-pública"}, {"valor": 2, "palabra": "gobierno-nacional"}, {"valor": 1, "palabra": "informo-personal"}, {"valor": 1, "palabra": "pública-provincial"}, {"valor": 1, "palabra": "provincial-disponibles"}, {"valor": 1, "palabra": "disponibles-recibos"}, {"valor": 1, "palabra": "recibos-sueldo"}, {"valor": 1, "palabra": "sueldo-correspondientes"}, {"valor": 1, "palabra": "correspondientes-aumentos"}, {"valor": 1, "palabra": "aumentos-anunciados"}, {"valor": 1, "palabra": "anunciados-pueden"}, {"valor": 1, "palabra": "pueden-consultar"}, {"valor": 1, "palabra": "consultar-online"}, {"valor": 1, "palabra": "online-usuario"}, {"valor": 1, "palabra": "usuario-contraseña"}, {"valor": 1, "palabra": "contraseña-además"}, {"valor": 1, "palabra": "además-recuerdo"}, {"valor": 1, "palabra": "recuerdo-haberes"}, {"valor": 1, "palabra": "haberes-personal"}, {"valor": 1, "palabra": "pública-jubilados"}, {"valor": 1, "palabra": "jubilados-pensionados"}, {"valor": 1, "palabra": "pensionados-retirados"}, {"valor": 1, "palabra": "retirados-estarán"}, {"valor": 1, "palabra": "estarán-también"}, {"valor": 1, "palabra": "también-acreditados"}, {"valor": 1, "palabra": "acreditados-jueves"}, {"valor": 1, "palabra": "jueves-gestión"}, {"valor": 1, "palabra": "gestión-exelente"}], "ARG - LUCAS ROMERO SPINELLI - FB": [{"valor": 1, "palabra": "participamos-edición"}, {"valor": 1, "palabra": "edición-evento"}, {"valor": 1, "palabra": "evento-cientos"}, {"valor": 1, "palabra": "cientos-cooperativas"}, {"valor": 1, "palabra": "cooperativas-locales"}, {"valor": 1, "palabra": "locales-regionales"}, {"valor": 1, "palabra": "regionales-nacionales"}, {"valor": 1, "palabra": "nacionales-internacionales"}, {"valor": 1, "palabra": "internacionales-tengan"}, {"valor": 1, "palabra": "tengan-oportunidad"}, {"valor": 1, "palabra": "oportunidad-conocer"}, {"valor": 1, "palabra": "conocer-trabajos"}, {"valor": 1, "palabra": "trabajos-producción"}, {"valor": 1, "palabra": "producción-oferta"}, {"valor": 1, "palabra": "oferta-servicios"}, {"valor": 1, "palabra": "servicios-felicitaciones"}, {"valor": 1, "palabra": "felicitaciones-importante"}, {"valor": 1, "palabra": "importante-oportunidad"}, {"valor": 1, "palabra": "oportunidad-emprendedores"}, {"valor": 1, "palabra": "emprendedores-principalmente"}, {"valor": 1, "palabra": "principalmente-felicidades"}, {"valor": 1, "palabra": "felicidades-vergonzoso"}, {"valor": 1, "palabra": "vergonzoso-docentes"}, {"valor": 1, "palabra": "docentes-policías"}, {"valor": 1, "palabra": "policías-agentes"}, {"valor": 1, "palabra": "agentes-primero"}, {"valor": 1, "palabra": "primero-resolve"}, {"valor": 1, "palabra": "resolve-cuestiones"}, {"valor": 1, "palabra": "cuestiones-importantes"}, {"valor": 1, "palabra": "importantes-viajes"}]}, "2024-05-27-2024-05-27": {"ARG - Medios Misiones - FB": [], "ARG - HUGO PASSALACQUA - FB": [], "ARG - LUCAS ROMERO SPINELLI - FB": [{"valor": 1, "palabra": "auditoría-ustedes"}, {"valor": 1, "palabra": "ustedes-raulsito"}, {"valor": 1, "palabra": "raulsito-denunciar"}, {"valor": 1, "palabra": "denunciar-cobardes"}, {"valor": 1, "palabra": "cobardes-caradura"}, {"valor": 1, "palabra": "caradura-luquitas"}, {"valor": 1, "palabra": "luquitas-entiendo"}, {"valor": 1, "palabra": "entiendo-influencia"}, {"valor": 1, "palabra": "influencia-política"}, {"valor": 1, "palabra": "política-cobrando"}, {"valor": 1, "palabra": "cobrando-arriba"}, {"valor": 1, "palabra": "arriba-suegro"}, {"valor": 1, "palabra": "suegro-rovira"}, {"valor": 1, "palabra": "rovira-fabriquita"}, {"valor": 1, "palabra": "fabriquita-fideicomiso"}, {"valor": 1, "palabra": "fideicomiso-misioneros"}, {"valor": 1, "palabra": "misioneros-amiguito"}, {"valor": 1, "palabra": "amiguito-drones"}, {"valor": 1, "palabra": "drones-pasalaucha"}, {"valor": 1, "palabra": "pasalaucha-nosotros"}, {"valor": 1, "palabra": "nosotros-sabemos"}, {"valor": 1, "palabra": "sabemos-ustedes"}, {"valor": 1, "palabra": "ustedes-también"}, {"valor": 1, "palabra": "también-cientos"}, {"valor": 1, "palabra": "cientos-trabajadores"}, {"valor": 1, "palabra": "trabajadores-provincia"}, {"valor": 1, "palabra": "provincia-lluvia"}, {"valor": 1, "palabra": "lluvia-avenida"}, {"valor": 1, "palabra": "avenida-uruguay"}, {"valor": 1, "palabra": "uruguay-uruguay"}]}}