{"2024-07-04-2024-07-04": {"ARG - Medios Misiones - FB": [{"valor": 80, "palabra": "misiones"}, {"valor": 47, "palabra": "cuando"}, {"valor": 46, "palabra": "posadas"}, {"valor": 46, "palabra": "argentina"}, {"valor": 37, "palabra": "porque"}, {"valor": 33, "palabra": "provincia"}, {"valor": 30, "palabra": "noticia"}, {"valor": 29, "palabra": "tienen"}, {"valor": 29, "palabra": "gobierno"}, {"valor": 28, "palabra": "felicitaciones"}, {"valor": 27, "palabra": "nacional"}, {"valor": 24, "palabra": "siempre"}, {"valor": 24, "palabra": "también"}, {"valor": 24, "palabra": "completa"}, {"valor": 23, "palabra": "presidente"}, {"valor": 22, "palabra": "jueves"}, {"valor": 22, "palabra": "después"}, {"valor": 21, "palabra": "turismo"}, {"valor": 20, "palabra": "semana"}, {"valor": 20, "palabra": "wwwreddemediosmisionescomar"}, {"valor": 19, "palabra": "vergüenza"}, {"valor": 19, "palabra": "fanáticos"}, {"valor": 19, "palabra": "autódromo"}, {"valor": 19, "palabra": "policía"}, {"valor": 19, "palabra": "centro"}, {"valor": 19, "palabra": "justicia"}, {"valor": 19, "palabra": "tiempo"}, {"valor": 17, "palabra": "gracias"}, {"valor": 17, "palabra": "carretera"}, {"valor": 17, "palabra": "provincial"}, {"valor": 17, "palabra": "trabajo"}, {"valor": 17, "palabra": "misioneros"}, {"valor": 16, "palabra": "partido"}, {"valor": 16, "palabra": "quieren"}, {"valor": 16, "palabra": "viernes"}, {"valor": 16, "palabra": "además"}, {"valor": 16, "palabra": "fueron"}, {"valor": 16, "palabra": "política"}, {"valor": 15, "palabra": "grande"}, {"valor": 15, "palabra": "momento"}], "ARG - HUGO PASSALACQUA - FB": [{"valor": 3, "palabra": "parásitos"}, {"valor": 3, "palabra": "política"}, {"valor": 3, "palabra": "trabajo"}, {"valor": 2, "palabra": "políticos"}, {"valor": 2, "palabra": "vividores"}, {"valor": 2, "palabra": "estado"}, {"valor": 2, "palabra": "misiones"}, {"valor": 2, "palabra": "importante"}, {"valor": 2, "palabra": "empresariales"}, {"valor": 1, "palabra": "escribió"}, {"valor": 1, "palabra": "alguna"}, {"valor": 1, "palabra": "aceptarla"}, {"valor": 1, "palabra": "concepto"}, {"valor": 1, "palabra": "aplica"}, {"valor": 1, "palabra": "conocen"}, {"valor": 1, "palabra": "sacrificada"}, {"valor": 1, "palabra": "ostentan"}, {"valor": 1, "palabra": "fáciles"}, {"valor": 1, "palabra": "privilegios"}, {"valor": 1, "palabra": "viviendo"}, {"valor": 1, "palabra": "pueblo"}, {"valor": 1, "palabra": "parásita"}, {"valor": 1, "palabra": "vividora"}, {"valor": 1, "palabra": "oportunidad"}, {"valor": 1, "palabra": "visitar"}, {"valor": 1, "palabra": "parque"}, {"valor": 1, "palabra": "industrial"}, {"valor": 1, "palabra": "aprender"}, {"valor": 1, "palabra": "riqueza"}, {"valor": 1, "palabra": "trabajando"}, {"valor": 1, "palabra": "siendo"}, {"valor": 1, "palabra": "amigos"}, {"valor": 1, "palabra": "marcelo"}, {"valor": 1, "palabra": "delfino"}, {"valor": 1, "palabra": "distrito"}, {"valor": 1, "palabra": "vialidad"}, {"valor": 1, "palabra": "nacional"}, {"valor": 1, "palabra": "gerónimo"}, {"valor": 1, "palabra": "andújar"}, {"valor": 1, "palabra": "responsabilidad"}], "ARG - LUCAS ROMERO SPINELLI - FB": []}, "2024-07-05-2024-07-05": {"ARG - Medios Misiones - FB": [{"valor": 87, "palabra": "misiones"}, {"valor": 55, "palabra": "posadas"}, {"valor": 52, "palabra": "argentina"}, {"valor": 38, "palabra": "trabajo"}, {"valor": 36, "palabra": "gobierno"}, {"valor": 34, "palabra": "provincia"}, {"valor": 33, "palabra": "noticia"}, {"valor": 29, "palabra": "completa"}, {"valor": 28, "palabra": "provincial"}, {"valor": 28, "palabra": "porque"}, {"valor": 27, "palabra": "libertad"}, {"valor": 25, "palabra": "nacional"}, {"valor": 24, "palabra": "también"}, {"valor": 24, "palabra": "wwwreddemediosmisionescomar"}, {"valor": 23, "palabra": "presidente"}, {"valor": 23, "palabra": "siempre"}, {"valor": 23, "palabra": "gracias"}, {"valor": 22, "palabra": "misionero"}, {"valor": 22, "palabra": "productores"}, {"valor": 21, "palabra": "misioneros"}, {"valor": 21, "palabra": "viernes"}, {"valor": 21, "palabra": "ministro"}, {"valor": 21, "palabra": "cuando"}, {"valor": 19, "palabra": "turismo"}, {"valor": 19, "palabra": "tienen"}, {"valor": 18, "palabra": "penales"}, {"valor": 18, "palabra": "semana"}, {"valor": 18, "palabra": "sector"}, {"valor": 18, "palabra": "empresa"}, {"valor": 18, "palabra": "estamos"}, {"valor": 17, "palabra": "dólares"}, {"valor": 17, "palabra": "felicitaciones"}, {"valor": 16, "palabra": "oficial"}, {"valor": 16, "palabra": "billetes"}, {"valor": 16, "palabra": "tiempo"}, {"valor": 15, "palabra": "semifinales"}, {"valor": 15, "palabra": "estado"}, {"valor": 15, "palabra": "nuestra"}, {"valor": 15, "palabra": "mañana"}, {"valor": 15, "palabra": "camión"}], "ARG - HUGO PASSALACQUA - FB": [{"valor": 4, "palabra": "circunscripción"}, {"valor": 4, "palabra": "judicial"}, {"valor": 3, "palabra": "segunda"}, {"valor": 3, "palabra": "política"}, {"valor": 2, "palabra": "eldorado"}, {"valor": 2, "palabra": "panambí"}, {"valor": 2, "palabra": "puerto"}, {"valor": 2, "palabra": "iguazú"}, {"valor": 2, "palabra": "adriana"}, {"valor": 2, "palabra": "tercera"}, {"valor": 2, "palabra": "instrucción"}, {"valor": 2, "palabra": "políticos"}, {"valor": 2, "palabra": "privilegios"}, {"valor": 1, "palabra": "rosanna"}, {"valor": 1, "palabra": "venchiarutti"}, {"valor": 1, "palabra": "sartori"}, {"valor": 1, "palabra": "ministros"}, {"valor": 1, "palabra": "presenciamos"}, {"valor": 1, "palabra": "jueces"}, {"valor": 1, "palabra": "defensores"}, {"valor": 1, "palabra": "agentes"}, {"valor": 1, "palabra": "judiciales"}, {"valor": 1, "palabra": "momento"}, {"valor": 1, "palabra": "importante"}, {"valor": 1, "palabra": "servicio"}, {"valor": 1, "palabra": "justicia"}, {"valor": 1, "palabra": "municipios"}, {"valor": 1, "palabra": "andino"}, {"valor": 1, "palabra": "tribunal"}, {"valor": 1, "palabra": "lorena"}, {"valor": 1, "palabra": "letrada"}, {"valor": 1, "palabra": "juzgado"}, {"valor": 1, "palabra": "categoría"}, {"valor": 1, "palabra": "flavia"}, {"valor": 1, "palabra": "carolina"}, {"valor": 1, "palabra": "valenzuela"}, {"valor": 1, "palabra": "defensora"}, {"valor": 1, "palabra": "oficial"}, {"valor": 1, "palabra": "correccional"}, {"valor": 1, "palabra": "menores"}], "ARG - LUCAS ROMERO SPINELLI - FB": [{"valor": 4, "palabra": "pronta"}, {"valor": 3, "palabra": "recuperación"}, {"valor": 3, "palabra": "política"}, {"valor": 2, "palabra": "importante"}, {"valor": 2, "palabra": "bendiga"}, {"valor": 2, "palabra": "políticos"}, {"valor": 2, "palabra": "privilegios"}, {"valor": 2, "palabra": "grande"}, {"valor": 1, "palabra": "aunque"}, {"valor": 1, "palabra": "postoperatorio"}, {"valor": 1, "palabra": "cirugía"}, {"valor": 1, "palabra": "rodilla"}, {"valor": 1, "palabra": "ausente"}, {"valor": 1, "palabra": "evento"}, {"valor": 1, "palabra": "tecnología"}, {"valor": 1, "palabra": "región"}, {"valor": 1, "palabra": "tercera"}, {"valor": 1, "palabra": "provincial"}, {"valor": 1, "palabra": "robótica"}, {"valor": 1, "palabra": "reunió"}, {"valor": 1, "palabra": "competidores"}, {"valor": 1, "palabra": "participantes"}, {"valor": 1, "palabra": "integrantes"}, {"valor": 1, "palabra": "equipos"}, {"valor": 1, "palabra": "acompañó"}, {"valor": 1, "palabra": "visita"}, {"valor": 1, "palabra": "stelatto"}, {"valor": 1, "palabra": "juntos"}, {"valor": 1, "palabra": "pudimos"}, {"valor": 1, "palabra": "apreciar"}, {"valor": 1, "palabra": "estamos"}, {"valor": 1, "palabra": "viviendo"}, {"valor": 1, "palabra": "momento"}, {"valor": 1, "palabra": "innovación"}, {"valor": 1, "palabra": "construyendo"}, {"valor": 1, "palabra": "misiones"}, {"valor": 1, "palabra": "diferente"}, {"valor": 1, "palabra": "cuídate"}, {"valor": 1, "palabra": "operatorio"}, {"valor": 1, "palabra": "ospital"}]}, "2024-07-06-2024-07-06": {"ARG - Medios Misiones - FB": [{"valor": 60, "palabra": "misiones"}, {"valor": 54, "palabra": "posadas"}, {"valor": 49, "palabra": "argentina"}, {"valor": 45, "palabra": "gobierno"}, {"valor": 44, "palabra": "libertad"}, {"valor": 43, "palabra": "cuando"}, {"valor": 42, "palabra": "porque"}, {"valor": 33, "palabra": "felicitaciones"}, {"valor": 31, "palabra": "estado"}, {"valor": 30, "palabra": "tienen"}, {"valor": 29, "palabra": "siempre"}, {"valor": 29, "palabra": "sábado"}, {"valor": 29, "palabra": "precios"}, {"valor": 28, "palabra": "justicia"}, {"valor": 27, "palabra": "provincia"}, {"valor": 27, "palabra": "votaron"}, {"valor": 26, "palabra": "turismo"}, {"valor": 25, "palabra": "tiempo"}, {"valor": 22, "palabra": "chicos"}, {"valor": 21, "palabra": "comprar"}, {"valor": 21, "palabra": "presidente"}, {"valor": 20, "palabra": "primera"}, {"valor": 20, "palabra": "provincial"}, {"valor": 19, "palabra": "carretera"}, {"valor": 19, "palabra": "semana"}, {"valor": 19, "palabra": "centro"}, {"valor": 19, "palabra": "muchos"}, {"valor": 19, "palabra": "noticia"}, {"valor": 18, "palabra": "también"}, {"valor": 18, "palabra": "nacional"}, {"valor": 18, "palabra": "completa"}, {"valor": 18, "palabra": "gracias"}, {"valor": 18, "palabra": "jajaja"}, {"valor": 17, "palabra": "autódromo"}, {"valor": 17, "palabra": "tenemos"}, {"valor": 17, "palabra": "carajo"}, {"valor": 16, "palabra": "productos"}, {"valor": 16, "palabra": "cuenta"}, {"valor": 16, "palabra": "misionero"}, {"valor": 16, "palabra": "estamos"}], "ARG - HUGO PASSALACQUA - FB": [{"valor": 1, "palabra": "docentes"}, {"valor": 1, "palabra": "corresponda"}, {"valor": 1, "palabra": "aumenta"}, {"valor": 1, "palabra": "decretosin"}, {"valor": 1, "palabra": "vergüenza"}, {"valor": 1, "palabra": "excelente"}], "ARG - LUCAS ROMERO SPINELLI - FB": [{"valor": 2, "palabra": "productores"}, {"valor": 2, "palabra": "bioinsumos"}, {"valor": 2, "palabra": "productor"}, {"valor": 2, "palabra": "recuperación"}, {"valor": 1, "palabra": "seguimos"}, {"valor": 1, "palabra": "trabajando"}, {"valor": 1, "palabra": "capacitación"}, {"valor": 1, "palabra": "nuestros"}, {"valor": 1, "palabra": "agrarios"}, {"valor": 1, "palabra": "aplicación"}, {"valor": 1, "palabra": "cultivos"}, {"valor": 1, "palabra": "caraguatay"}, {"valor": 1, "palabra": "llegamos"}, {"valor": 1, "palabra": "juntos"}, {"valor": 1, "palabra": "técnicos"}, {"valor": 1, "palabra": "misiones"}, {"valor": 1, "palabra": "recibido"}, {"valor": 1, "palabra": "asesoramiento"}, {"valor": 1, "palabra": "medioambiente"}, {"valor": 1, "palabra": "misionero"}, {"valor": 1, "palabra": "encima"}, {"valor": 1, "palabra": "agroecología"}, {"valor": 1, "palabra": "camino"}, {"valor": 1, "palabra": "lagarto"}, {"valor": 1, "palabra": "mierda"}, {"valor": 1, "palabra": "títere"}, {"valor": 1, "palabra": "rovira"}, {"valor": 1, "palabra": "inútiles"}, {"valor": 1, "palabra": "delincuentes"}, {"valor": 1, "palabra": "chorros"}, {"valor": 1, "palabra": "pudiera"}, {"valor": 1, "palabra": "hacerle"}, {"valor": 1, "palabra": "desaparecer"}, {"valor": 1, "palabra": "ustedes"}, {"valor": 1, "palabra": "lasalud"}, {"valor": 1, "palabra": "también"}, {"valor": 1, "palabra": "consumidor"}, {"valor": 1, "palabra": "felicitaciones"}, {"valor": 1, "palabra": "bendecida"}, {"valor": 1, "palabra": "lechuga"}]}, "2024-07-07-2024-07-07": {"ARG - Medios Misiones - FB": [{"valor": 74, "palabra": "misiones"}, {"valor": 54, "palabra": "posadas"}, {"valor": 49, "palabra": "cuando"}, {"valor": 43, "palabra": "inflación"}, {"valor": 41, "palabra": "gobierno"}, {"valor": 37, "palabra": "turismo"}, {"valor": 37, "palabra": "tienen"}, {"valor": 34, "palabra": "jajaja"}, {"valor": 33, "palabra": "argentina"}, {"valor": 28, "palabra": "también"}, {"valor": 28, "palabra": "porque"}, {"valor": 27, "palabra": "siempre"}, {"valor": 25, "palabra": "después"}, {"valor": 24, "palabra": "brasil"}, {"valor": 23, "palabra": "carretera"}, {"valor": 22, "palabra": "tiempo"}, {"valor": 22, "palabra": "bautista"}, {"valor": 21, "palabra": "laudelina"}, {"valor": 21, "palabra": "provincia"}, {"valor": 21, "palabra": "semana"}, {"valor": 21, "palabra": "mentira"}, {"valor": 20, "palabra": "paraguayos"}, {"valor": 19, "palabra": "américa"}, {"valor": 19, "palabra": "verdad"}, {"valor": 18, "palabra": "libertad"}, {"valor": 18, "palabra": "noticia"}, {"valor": 18, "palabra": "estamos"}, {"valor": 17, "palabra": "precios"}, {"valor": 16, "palabra": "domingo"}, {"valor": 16, "palabra": "primera"}, {"valor": 16, "palabra": "seguro"}, {"valor": 16, "palabra": "combustible"}, {"valor": 15, "palabra": "partido"}, {"valor": 15, "palabra": "nacional"}, {"valor": 15, "palabra": "economía"}, {"valor": 15, "palabra": "vergüenza"}, {"valor": 14, "palabra": "millones"}, {"valor": 14, "palabra": "mustang"}, {"valor": 14, "palabra": "justicia"}, {"valor": 14, "palabra": "momento"}], "ARG - HUGO PASSALACQUA - FB": [], "ARG - LUCAS ROMERO SPINELLI - FB": [{"valor": 1, "palabra": "productores"}, {"valor": 1, "palabra": "felicitaciones"}, {"valor": 1, "palabra": "espectacular"}, {"valor": 1, "palabra": "vicegobernador"}, {"valor": 1, "palabra": "precio"}, {"valor": 1, "palabra": "mudita"}, {"valor": 1, "palabra": "lechuga"}, {"valor": 1, "palabra": "compartió"}, {"valor": 1, "palabra": "brindó"}, {"valor": 1, "palabra": "aportes"}, {"valor": 1, "palabra": "alumnos"}, {"valor": 1, "palabra": "congreso"}, {"valor": 1, "palabra": "provincial"}, {"valor": 1, "palabra": "juventud"}, {"valor": 1, "palabra": "edición"}, {"valor": 1, "palabra": "manera"}, {"valor": 1, "palabra": "virtual"}, {"valor": 1, "palabra": "escuela"}, {"valor": 1, "palabra": "garupá"}]}, "2024-07-08-2024-07-08": {"ARG - Medios Misiones - FB": [{"valor": 40, "palabra": "misiones"}, {"valor": 31, "palabra": "argentina"}, {"valor": 30, "palabra": "noticia"}, {"valor": 29, "palabra": "siempre"}, {"valor": 27, "palabra": "familia"}, {"valor": 25, "palabra": "jajaja"}, {"valor": 22, "palabra": "posadas"}, {"valor": 22, "palabra": "felicitaciones"}, {"valor": 21, "palabra": "gobierno"}, {"valor": 20, "palabra": "semana"}, {"valor": 19, "palabra": "cuando"}, {"valor": 19, "palabra": "completa"}, {"valor": 19, "palabra": "wwwreddemediosmisionescomar"}, {"valor": 18, "palabra": "porque"}, {"valor": 16, "palabra": "corrientes"}, {"valor": 16, "palabra": "excelente"}, {"valor": 15, "palabra": "tienen"}, {"valor": 15, "palabra": "provincia"}, {"valor": 15, "palabra": "barrio"}, {"valor": 14, "palabra": "nacional"}, {"valor": 14, "palabra": "inflación"}, {"valor": 14, "palabra": "policía"}, {"valor": 14, "palabra": "buenos"}, {"valor": 14, "palabra": "felicidades"}, {"valor": 13, "palabra": "mientras"}, {"valor": 13, "palabra": "persona"}, {"valor": 13, "palabra": "merecido"}, {"valor": 12, "palabra": "hermano"}, {"valor": 12, "palabra": "contra"}, {"valor": 12, "palabra": "hombre"}, {"valor": 12, "palabra": "consumo"}, {"valor": 12, "palabra": "brasil"}, {"valor": 12, "palabra": "estamos"}, {"valor": 11, "palabra": "presidente"}, {"valor": 10, "palabra": "ciudad"}, {"valor": 10, "palabra": "trabajo"}, {"valor": 10, "palabra": "muchos"}, {"valor": 10, "palabra": "grande"}, {"valor": 10, "palabra": "provincial"}, {"valor": 10, "palabra": "temperaturas"}], "ARG - HUGO PASSALACQUA - FB": [{"valor": 2, "palabra": "fachinello"}, {"valor": 2, "palabra": "presidente"}, {"valor": 1, "palabra": "recibimos"}, {"valor": 1, "palabra": "ministro"}, {"valor": 1, "palabra": "industria"}, {"valor": 1, "palabra": "federico"}, {"valor": 1, "palabra": "alfredo"}, {"valor": 1, "palabra": "gonzález"}, {"valor": 1, "palabra": "guillermo"}, {"valor": 1, "palabra": "secretario"}, {"valor": 1, "palabra": "general"}, {"valor": 1, "palabra": "interior"}, {"valor": 1, "palabra": "gerardo"}, {"valor": 1, "palabra": "beltran"}, {"valor": 1, "palabra": "estamos"}, {"valor": 1, "palabra": "trabajando"}, {"valor": 1, "palabra": "potenciar"}, {"valor": 1, "palabra": "misioneras"}, {"valor": 1, "palabra": "posicionarlas"}, {"valor": 1, "palabra": "mercado"}, {"valor": 1, "palabra": "brasilero"}, {"valor": 1, "palabra": "también"}, {"valor": 1, "palabra": "buscamos"}, {"valor": 1, "palabra": "fortalecer"}, {"valor": 1, "palabra": "jóvenes"}, {"valor": 1, "palabra": "empresarios"}, {"valor": 1, "palabra": "futuro"}, {"valor": 1, "palabra": "productivo"}, {"valor": 1, "palabra": "provincia"}], "ARG - LUCAS ROMERO SPINELLI - FB": [{"valor": 1, "palabra": "destruyendo"}, {"valor": 1, "palabra": "produccion"}, {"valor": 1, "palabra": "misiones"}, {"valor": 1, "palabra": "cambió"}, {"valor": 1, "palabra": "migajas"}, {"valor": 1, "palabra": "colonos"}, {"valor": 1, "palabra": "políticos"}, {"valor": 1, "palabra": "corruptos"}]}, "2024-07-09-2024-07-09": {"ARG - Medios Misiones - FB": [{"valor": 46, "palabra": "misiones"}, {"valor": 22, "palabra": "argentina"}, {"valor": 21, "palabra": "provincia"}, {"valor": 19, "palabra": "porque"}, {"valor": 17, "palabra": "cuando"}, {"valor": 16, "palabra": "patria"}, {"valor": 15, "palabra": "independencia"}, {"valor": 15, "palabra": "gobernadores"}, {"valor": 15, "palabra": "gobernador"}, {"valor": 14, "palabra": "posadas"}, {"valor": 13, "palabra": "también"}, {"valor": 12, "palabra": "tienen"}, {"valor": 11, "palabra": "estamos"}, {"valor": 11, "palabra": "presidente"}, {"valor": 11, "palabra": "gobierno"}, {"valor": 11, "palabra": "siempre"}, {"valor": 9, "palabra": "además"}, {"valor": 9, "palabra": "passalacqua"}, {"valor": 9, "palabra": "misionero"}, {"valor": 9, "palabra": "puntos"}, {"valor": 9, "palabra": "jajajaja"}, {"valor": 8, "palabra": "tiempo"}, {"valor": 8, "palabra": "turismo"}, {"valor": 8, "palabra": "nuestra"}, {"valor": 8, "palabra": "tenemos"}, {"valor": 8, "palabra": "javier"}, {"valor": 8, "palabra": "reforma"}, {"valor": 8, "palabra": "persona"}, {"valor": 7, "palabra": "francia"}, {"valor": 7, "palabra": "temperaturas"}, {"valor": 7, "palabra": "tucumán"}, {"valor": 7, "palabra": "hombre"}, {"valor": 7, "palabra": "provincial"}, {"valor": 7, "palabra": "alberdi"}, {"valor": 7, "palabra": "mercado"}, {"valor": 7, "palabra": "primera"}, {"valor": 7, "palabra": "grande"}, {"valor": 7, "palabra": "accidente"}, {"valor": 7, "palabra": "argentinos"}, {"valor": 7, "palabra": "apertura"}], "ARG - HUGO PASSALACQUA - FB": [{"valor": 11, "palabra": "aniversario"}, {"valor": 6, "palabra": "ciudad"}, {"valor": 5, "palabra": "gobernador"}, {"valor": 3, "palabra": "patria"}, {"valor": 3, "palabra": "compromiso"}, {"valor": 3, "palabra": "independencia"}, {"valor": 3, "palabra": "siempre"}, {"valor": 3, "palabra": "felicidades"}, {"valor": 3, "palabra": "misionero"}, {"valor": 3, "palabra": "respeto"}, {"valor": 2, "palabra": "argentinos"}, {"valor": 2, "palabra": "argentina"}, {"valor": 2, "palabra": "federal"}, {"valor": 2, "palabra": "passalacqua"}, {"valor": 2, "palabra": "ladrones"}, {"valor": 2, "palabra": "misiones"}, {"valor": 2, "palabra": "políticos"}, {"valor": 2, "palabra": "pueblo"}, {"valor": 2, "palabra": "convenir"}, {"valor": 2, "palabra": "queremos"}, {"valor": 2, "palabra": "provincia"}, {"valor": 1, "palabra": "cumple"}, {"valor": 1, "palabra": "felices"}, {"valor": 1, "palabra": "tucumán"}, {"valor": 1, "palabra": "distintivo"}, {"valor": 1, "palabra": "colegas"}, {"valor": 1, "palabra": "gobernadores"}, {"valor": 1, "palabra": "presidente"}, {"valor": 1, "palabra": "javier"}, {"valor": 1, "palabra": "ratificamos"}, {"valor": 1, "palabra": "trabajar"}, {"valor": 1, "palabra": "banderías"}, {"valor": 1, "palabra": "políticas"}, {"valor": 1, "palabra": "lograr"}, {"valor": 1, "palabra": "deseamos"}, {"valor": 1, "palabra": "próspero"}, {"valor": 1, "palabra": "merecemos"}, {"valor": 1, "palabra": "vivaaa"}, {"valor": 1, "palabra": "cuidad"}, {"valor": 1, "palabra": "oberami"}], "ARG - LUCAS ROMERO SPINELLI - FB": [{"valor": 1, "palabra": "excelente"}, {"valor": 1, "palabra": "gestión"}, {"valor": 1, "palabra": "felicitaciones"}]}, "2024-07-10-2024-07-10": {"ARG - Medios Misiones - FB": [{"valor": 76, "palabra": "misiones"}, {"valor": 58, "palabra": "posadas"}, {"valor": 45, "palabra": "argentina"}, {"valor": 39, "palabra": "justicia"}, {"valor": 30, "palabra": "nacional"}, {"valor": 28, "palabra": "miércoles"}, {"valor": 24, "palabra": "gobierno"}, {"valor": 23, "palabra": "buenos"}, {"valor": 23, "palabra": "cuando"}, {"valor": 23, "palabra": "noticia"}, {"valor": 22, "palabra": "américa"}, {"valor": 22, "palabra": "completa"}, {"valor": 21, "palabra": "ciudad"}, {"valor": 21, "palabra": "mañana"}, {"valor": 20, "palabra": "porque"}, {"valor": 19, "palabra": "durante"}, {"valor": 19, "palabra": "provincia"}, {"valor": 19, "palabra": "velocidad"}, {"valor": 19, "palabra": "wwwreddemediosmisionescomar"}, {"valor": 18, "palabra": "también"}, {"valor": 18, "palabra": "contra"}, {"valor": 17, "palabra": "después"}, {"valor": 17, "palabra": "provincial"}, {"valor": 16, "palabra": "independencia"}, {"valor": 15, "palabra": "fútbol"}, {"valor": 14, "palabra": "accidente"}, {"valor": 14, "palabra": "gobernador"}, {"valor": 14, "palabra": "familia"}, {"valor": 13, "palabra": "online"}, {"valor": 13, "palabra": "federal"}, {"valor": 13, "palabra": "selección"}, {"valor": 13, "palabra": "temperaturas"}, {"valor": 13, "palabra": "estaba"}, {"valor": 13, "palabra": "chicos"}, {"valor": 13, "palabra": "nombre"}, {"valor": 13, "palabra": "gracias"}, {"valor": 12, "palabra": "semana"}, {"valor": 12, "palabra": "conductor"}, {"valor": 12, "palabra": "paraguay"}, {"valor": 12, "palabra": "tienen"}], "ARG - HUGO PASSALACQUA - FB": [{"valor": 6, "palabra": "misiones"}, {"valor": 5, "palabra": "gobernador"}, {"valor": 3, "palabra": "posadas"}, {"valor": 3, "palabra": "siempre"}, {"valor": 2, "palabra": "nuestra"}, {"valor": 2, "palabra": "independencia"}, {"valor": 2, "palabra": "verdad"}, {"valor": 2, "palabra": "provincia"}, {"valor": 2, "palabra": "distintos"}, {"valor": 2, "palabra": "inmigrantes"}, {"valor": 2, "palabra": "fiesta"}, {"valor": 2, "palabra": "patria"}, {"valor": 2, "palabra": "bendiciones"}, {"valor": 2, "palabra": "vergüenza"}, {"valor": 2, "palabra": "passalacqua"}, {"valor": 2, "palabra": "excelente"}, {"valor": 2, "palabra": "pueblo"}, {"valor": 2, "palabra": "passalaqua"}, {"valor": 1, "palabra": "catedral"}, {"valor": 1, "palabra": "compartimos"}, {"valor": 1, "palabra": "tedéum"}, {"valor": 1, "palabra": "celebrado"}, {"valor": 1, "palabra": "sebastián"}, {"valor": 1, "palabra": "escalante"}, {"valor": 1, "palabra": "vicario"}, {"valor": 1, "palabra": "general"}, {"valor": 1, "palabra": "diócesis"}, {"valor": 1, "palabra": "recordamos"}, {"valor": 1, "palabra": "patriotas"}, {"valor": 1, "palabra": "hicieron"}, {"valor": 1, "palabra": "posible"}, {"valor": 1, "palabra": "elevamos"}, {"valor": 1, "palabra": "oraciones"}, {"valor": 1, "palabra": "familia"}, {"valor": 1, "palabra": "misionera"}, {"valor": 1, "palabra": "justicia"}, {"valor": 1, "palabra": "aparición"}, {"valor": 1, "palabra": "nuestros"}, {"valor": 1, "palabra": "representantes"}, {"valor": 1, "palabra": "circenses"}], "ARG - LUCAS ROMERO SPINELLI - FB": []}, "2024-07-11-2024-07-11": {"ARG - Medios Misiones - FB": [{"valor": 4, "palabra": "turistas"}, {"valor": 4, "palabra": "pueblo"}, {"valor": 3, "palabra": "tienen"}, {"valor": 3, "palabra": "electos"}, {"valor": 2, "palabra": "nacimiento"}, {"valor": 2, "palabra": "mellizos"}, {"valor": 2, "palabra": "presidente"}, {"valor": 2, "palabra": "tenemos"}, {"valor": 2, "palabra": "cuando"}, {"valor": 2, "palabra": "elegir"}, {"valor": 2, "palabra": "comentarios"}, {"valor": 2, "palabra": "jueces"}, {"valor": 1, "palabra": "hormigueros"}, {"valor": 1, "palabra": "gigantes"}, {"valor": 1, "palabra": "récord"}, {"valor": 1, "palabra": "reintroducción"}, {"valor": 1, "palabra": "múltiple"}, {"valor": 1, "palabra": "población"}, {"valor": 1, "palabra": "reintroducida"}, {"valor": 1, "palabra": "primer"}, {"valor": 1, "palabra": "registro"}, {"valor": 1, "palabra": "especie"}, {"valor": 1, "palabra": "equipo"}, {"valor": 1, "palabra": "néstor"}, {"valor": 1, "palabra": "lorenzo"}, {"valor": 1, "palabra": "impuso"}, {"valor": 1, "palabra": "jefferson"}, {"valor": 1, "palabra": "celeste"}, {"valor": 1, "palabra": "marcelo"}, {"valor": 1, "palabra": "bielsa"}, {"valor": 1, "palabra": "jugando"}, {"valor": 1, "palabra": "complemento"}, {"valor": 1, "palabra": "expulsión"}, {"valor": 1, "palabra": "domingo"}, {"valor": 1, "palabra": "definición"}, {"valor": 1, "palabra": "edición"}, {"valor": 1, "palabra": "impresa"}, {"valor": 1, "palabra": "jueves"}, {"valor": 1, "palabra": "uruguay"}, {"valor": 1, "palabra": "ahhhhh"}], "ARG - HUGO PASSALACQUA - FB": [], "ARG - LUCAS ROMERO SPINELLI - FB": []}}